label_maker_dask/__init__.py
label_maker_dask/filter.py
label_maker_dask/label.py
label_maker_dask/main.py
label_maker_dask/result.py
label_maker_dask/utils.py
label_maker_dask-0.1.2.dist-info/LICENSE
label_maker_dask-0.1.2.dist-info/METADATA
label_maker_dask-0.1.2.dist-info/WHEEL
label_maker_dask-0.1.2.dist-info/top_level.txt
label_maker_dask-0.1.2.dist-info/RECORD
