Metadata-Version: 2.1
Name: label-maker-dask
Version: 0.1.2
Summary: Run label maker as a dask job
Home-page: https://github.com/developmentseed/label-maker-dask
Author: Drew Bollinger
Author-email: drew@developmentseed.org
License: BSD
Platform: UNKNOWN
Classifier: Intended Audience :: Information Technology
Classifier: Intended Audience :: Science/Research
Classifier: License :: OSI Approved :: BSD License
Classifier: Programming Language :: Python :: 3.6
Classifier: Topic :: Scientific/Engineering :: GIS
Requires-Python: >=3.6
License-File: LICENSE
Requires-Dist: dask
Requires-Dist: mapbox-vector-tile
Requires-Dist: mercantile
Requires-Dist: numpy
Requires-Dist: Pillow
Requires-Dist: rasterio
Requires-Dist: requests
Requires-Dist: rio-tiler (>=2)
Requires-Dist: shapely
Provides-Extra: test
Requires-Dist: pytest ; extra == 'test'
